[
  {
    "sliders": [
      {
        "name": "Test Font One",
        "size": "160.74 KB",

        "img": "https://mlqmtwka8c9g.i.optimole.com/gOh5_1g.Ga1T~1cfa5/w:auto/h:auto/q:75/https://www.competethemes.com/wp-content/uploads/2018/11/google-fonts.png",
        "url": "https://github.com/Kyawkk/MIUI-Font-Changer/raw/master/Fonts/Myanmar/Kamjing.ttf?raw=true"
      },
      {
        "name": "Test Font Two",
        "size": "160.74 KB",

        "img": "https://developer.apple.com/news/images/og/fonts-og.jpg",
        "url": "https://github.com/Kyawkk/MIUI-Font-Changer/raw/master/Fonts/Myanmar/Kamjing.ttf?raw=true"
      },
      {
        "name": "Test Font Three",
        "size": "160.74 KB",

        "img": "https://fontsme.com/wp-data/p/24/15024/slide/poppins-s0.png",
        "url": "https://github.com/Kyawkk/MIUI-Font-Changer/raw/master/Fonts/Myanmar/Kamjing.ttf?raw=true"
      },
      {
        "name": "Test Font Four",
        "size": "160.74 KB",

        "img": "https://i2.wp.com/www.freefonts.io/wp-content/uploads/2016/08/open-sans-font-5-big.png?fit=1024%2C512&ssl=1",
        "url": "https://github.com/Kyawkk/MIUI-Font-Changer/raw/master/Fonts/Myanmar/Kamjing.ttf?raw=true"
      }
    ]
  },
  {
    "categories": [
      {
        "title": "Emoji",
        "url": "https://github.com/Kyawkk/MIUI-Font-Changer/raw/master/emoji.json",
        "data": [
          {
            "name": "Android.L",
            "size": "5.13 MB",
            "image": "https://i.ibb.co/ssrShQx/Android-L.png",
            "url": "https://github.com/Kyawkk/MIUI-Font-Changer/raw/master/Fonts/Emoji/Android.L.ttf?raw=true"
          },
          {
            "name": "Android_11_Beta",
            "size": "9.71 MB",
            "image": "https://i.ibb.co/pwR0g6b/Android-11.png",
            "url": "https://github.com/Kyawkk/MIUI-Font-Changer/raw/master/Fonts/Emoji/Android_11_Beta.ttf?raw=true"
          },
          {
            "name": "Android_11",
            "size": "10.40 MB",
            "image": "https://i.ibb.co/pwR0g6b/Android-11.png",
            "url": "https://github.com/Kyawkk/MIUI-Font-Changer/raw/master/Fonts/Emoji/Android_11.ttf?raw=true"
          },
          {
            "name": "Android_12_UNRELEASED",
            "size": "10.06 MB",
            "image": "https://i.ibb.co/pwR0g6b/Android-11.png",
            "url": "https://github.com/Kyawkk/MIUI-Font-Changer/raw/master/Fonts/Emoji/Android_12_UNRELEASED.ttf?raw=true"
          }
        ]
      },
      {
        "title": "English",
        "url": "https://github.com/Kyawkk/MIUI-Font-Changer/raw/master/english.json",
        "data": [
          {
            "name": "8th Element Bold",
            "size": "63.58 KB",
            "image": "https://i.ibb.co/rtw6whj/8th-Element.png",
            "url": "https://github.com/Kyawkk/MIUI-Font-Changer/raw/master/Fonts/English/8th Element Bold.ttf?raw=true"
          },
          {
            "name": "8th Element",
            "size": "80.81 KB",
            "image": "https://i.ibb.co/CH7s9k9/8th-Element-Bold.png",
            "url": "https://github.com/Kyawkk/MIUI-Font-Changer/raw/master/Fonts/English/8th Element.ttf?raw=true"
          },
          {
            "name": "American Typewriter",
            "size": "41.12 KB",
            "image": "https://i.ibb.co/nr8bXks/American-Typewriter.png",
            "url": "https://github.com/Kyawkk/MIUI-Font-Changer/raw/master/Fonts/English/American Typewriter.otf?raw=true"
          },
          {
            "name": "Arista 2.0",
            "size": "74.37 KB",
            "image": "https://i.ibb.co/1Zq7S7n/Arista-2-0.png",
            "url": "https://github.com/Kyawkk/MIUI-Font-Changer/raw/master/Fonts/English/Arista 2.0.ttf?raw=true"
          }
        ]
      },
      {
        "title": "Myanmar",
        "url": "https://github.com/Kyawkk/MIUI-Font-Changer/raw/master/myanmar.json",
        "data": [
          {
            "name": "Myanmar One",
            "size": "225.24 KB",
            "image": "https://i.ibb.co/rfWKvW4/Kamjing.png",

            "url": "https://github.com/Kyawkk/MIUI-Font-Changer/raw/master/Fonts/Myanmar/Kamjing.ttf?raw=true"
          },
          {
            "name": "Myanmar Two",
            "size": "347.08 KB",
            "image": "https://i.ibb.co/QNvf7rV/KT-02.png",

            "url": "https://github.com/Kyawkk/MIUI-Font-Changer/raw/master/Fonts/Myanmar/KT_02.ttf?raw=true"
          },
          {
            "name": "Myanmar Three",
            "size": "160.74 KB",
            "image": "https://i.ibb.co/648Xnpy/KT-03.png",

            "url": "https://github.com/Kyawkk/MIUI-Font-Changer/raw/master/Fonts/Myanmar/KT_03.ttf?raw=true"
          },
          {
            "name": "Myanmar Four",
            "size": "59.60 KB",
            "image": "https://i.ibb.co/Kqz2MX6/Masterpiece-Uni-Round.png",

            "url": "https://github.com/Kyawkk/MIUI-Font-Changer/raw/master/Fonts/Myanmar/MasterpieceUniRound.ttf?raw=true"
          }
        ]
      },
      {
        "title": "Stylish",
        "url": "stylish url",
        "data": [
          {
            "name": "Stylish One",
            "size": "225.24 KB",
            "image": "",

            "url": "https://github.com/Kyawkk/MIUI-Font-Changer/raw/master/Fonts/Myanmar/Kamjing.ttf?raw=true"
          },
          {
            "name": "Stylish Two",
            "size": "347.08 KB",
            "image": "",

            "url": "https://github.com/Kyawkk/MIUI-Font-Changer/raw/master/Fonts/Myanmar/KT_02.ttf?raw=true"
          },
          {
            "name": "Stylish Three",
            "size": "160.74 KB",
            "image": "",

            "url": "https://github.com/Kyawkk/MIUI-Font-Changer/raw/master/Fonts/Myanmar/KT_03.ttf?raw=true"
          },
          {
            "name": "Stylish Four",
            "size": "59.60 KB",
            "image": "",

            "url": "https://github.com/Kyawkk/MIUI-Font-Changer/raw/master/Fonts/Myanmar/MasterpieceUniRound.ttf?raw=true"
          }
        ]
      }
    ]
  },
  {
    "languages": [
      {
        "name": "Arabic",
        "size": "116",
        "url": "https://github.com/Kyawkk/MIUI-Font-Changer/raw/master/arabic.json"
      },
      {
        "name": "Bengali",
        "size": "6",
        "url": "https://github.com/Kyawkk/MIUI-Font-Changer/raw/master/bengali.json"
      },
      {
        "name": "Cyrillic",
        "size": "164",
        "url": "https://github.com/Kyawkk/MIUI-Font-Changer/raw/master/cyrillic.json"
      },
      {
        "name": "Chinese",
        "size": "210",
        "url": ""
      },
      {
        "name": "Emoji",
        "size": "36",
        "url": "https://github.com/Kyawkk/MIUI-Font-Changer/raw/master/emoji.json"
      },
      {
        "name": "English",
        "size": "309",
        "url": "https://github.com/Kyawkk/MIUI-Font-Changer/raw/master/english.json"
      },
      {
        "name": "Gujarati",
        "size": "57",
        "url": "https://github.com/Kyawkk/MIUI-Font-Changer/raw/master/gujarati.json"
      },
      {
        "name": "Hindi",
        "size": "51",
        "url": "https://github.com/Kyawkk/MIUI-Font-Changer/raw/master/hindi.json"
      },
      {
        "name": "Japanese",
        "size": "83",
        "url": ""
      },
      {
        "name": "Kannada",
        "size": "8",
        "url": "https://github.com/Kyawkk/MIUI-Font-Changer/raw/master/kannada.json"
      },

      {
        "name": "Korean",
        "size": "146",
        "url": ""
      },
      {
        "name": "Myanmar",
        "size": "199",
        "url": "https://github.com/Kyawkk/MIUI-Font-Changer/raw/master/myanmar.json"
      },
      {
        "name": "Thai",
        "size": "410",
        "url": "https://github.com/Kyawkk/MIUI-Font-Changer/raw/master/thai.json"
      },
      {
        "name": "Traditional Chinese",
        "size": "41",
        "url": "https://github.com/Kyawkk/MIUI-Font-Changer/raw/master/traditional_chinese.json"
      }
    ]
  },
  {
    "font_resources": [
      {
        "image_url" : "https://mllj2j8xvfl0.i.optimole.com/Lsv2lkg.cHDL~36fa1/w:auto/h:auto/q:98/https://s15165.pcdn.co/wp-content/uploads/2020/04/best-google-fonts.jpg"
      }
    ]
  }
]
